ministats/__init__.py
ministats/bayes.py
ministats/calculus.py
ministats/confidence_intervals.py
ministats/estimators.py
ministats/formulas.py
ministats/hypothesis_tests.py
ministats/linear_models.py
ministats/probs.py
ministats/sampling.py
ministats/simulations.py
ministats/utils.py
ministats/book/__init__.py
ministats/book/figures.py
ministats/book/tables.py
ministats/plots/__init__.py
ministats/plots/cut_material.py
ministats/plots/figures.py
ministats/plots/probability.py
ministats/plots/regression.py
ministats-0.5.6.dist-info/LICENSE
ministats-0.5.6.dist-info/METADATA
ministats-0.5.6.dist-info/WHEEL
ministats-0.5.6.dist-info/top_level.txt
ministats-0.5.6.dist-info/RECORD
