Metadata-Version: 2.1
Name: ministats
Version: 0.5.6
Summary: Common statistical testing procedures used for STATS 101 topics. The code is intentionally simple to make it easy to follow for beginners.
Home-page: https://github.com/minireference/ministats
Author: Ivan Savov
Author-email: ivan@minireference.com
License: MIT license
Keywords: ministats
Classifier: Development Status :: 2 - Pre-Alpha
Classifier: Intended Audience :: Developers
Classifier: License :: OSI Approved :: MIT License
Classifier: Natural Language :: English
Classifier: Programming Language :: Python :: 3
Classifier: Programming Language :: Python :: 3.10
Classifier: Programming Language :: Python :: 3.11
Classifier: Programming Language :: Python :: 3.12
Classifier: Programming Language :: Python :: 3.13
Classifier: Programming Language :: Python :: 3.14
Requires-Python: >=3.10
License-File: LICENSE
Requires-Dist: matplotlib>=3.7
Requires-Dist: numpy>=1.24
Requires-Dist: scipy>=1.6
Requires-Dist: pandas>=2
Requires-Dist: seaborn>=0.13.2
Requires-Dist: statsmodels>=0.14.1
Requires-Dist: bambi==0.15.0
Requires-Dist: pymc==5.23.0
Requires-Dist: arviz
Requires-Dist: pingouin>=0.5.5
